jsonaea/Tools.py
jsonaea/__init__.py
Jsonaea-2025.5.10.dist-info/LICENSE
Jsonaea-2025.5.10.dist-info/METADATA
Jsonaea-2025.5.10.dist-info/WHEEL
Jsonaea-2025.5.10.dist-info/top_level.txt
Jsonaea-2025.5.10.dist-info/RECORD
