Metadata-Version: 2.2
Name: Jsonaea
Version: 2025.5.10
Summary: 将Arcaea游戏中铺面文件（x.aff）转换为json文件，亦可将json文件转换回铺面文件的实用库
Home-page: https://github.com/321bug/Jsonaea
Author: Begloon(321bug)
Author-email: bugbugbug321@163.com
Classifier: Programming Language :: Python :: 3
Classifier: License :: OSI Approved :: MIT License
Classifier: Operating System :: OS Independent
Requires-Python: >=3.0
License-File: LICENSE
Dynamic: author
Dynamic: author-email
Dynamic: classifier
Dynamic: description
Dynamic: description-content-type
Dynamic: home-page
Dynamic: requires-python
Dynamic: summary
